pyfmr/__init__.py
pyfmr/lib/fmr-darwin-10.6-amd64.dylib
pyfmr/lib/fmr-linux-amd64.so
pyfmr/lib/fmr-windows-4.0-amd64.dll
pyfmr-0.0.2.dist-info/METADATA
pyfmr-0.0.2.dist-info/RECORD
pyfmr-0.0.2.dist-info/WHEEL
pyfmr-0.0.2.dist-info/top_level.txt
