Metadata-Version: 2.1
Name: pyfmr
Version: 0.0.2
Summary: A python wrapper for FMR
Home-page: https://github.com/liuzl/pyfmr
Author: Zhanliang Liu
Author-email: liang@zliu.org
License: UNKNOWN
Platform: UNKNOWN
Classifier: Programming Language :: Python :: 3
Classifier: License :: OSI Approved :: Apache Software License
Classifier: Operating System :: OS Independent
